<?xml version="1.0" encoding="UTF-8"?>
<feature
      id="fr.opensagres.xdocreport.externals.jpa"
      label="JPA"
      version="1.0.0.qualifier">

   <description url="http://www.example.com/description">
      [Enter Feature Description here.]
   </description>

   <copyright url="http://www.example.com/copyright">
      [Enter Copyright Description here.]
   </copyright>

   <license url="http://www.example.com/license">
      [Enter License Description here.]
   </license>

  <plugin
         id="derby"
         download-size="0"
         install-size="0"
         version="0.0.0"
         unpack="false"/>
         
  <plugin
         id="com.springsource.org.apache.commons.dbcp"
         download-size="0"
         install-size="0"
         version="1.2.2.osgi"
         unpack="false"/>
               
  <plugin
         id="com.springsource.org.apache.commons.pool"
         download-size="0"
         install-size="0"
         version="0.0.0"
         unpack="false"/>
         
  <plugin
         id="spring-data-jpa"
         download-size="0"
         install-size="0"
         version="0.0.0"
         unpack="false"/>
  
  <plugin
         id="org.springframework.data.commons"
         download-size="0"
         install-size="0"
         version="0.0.0"
         unpack="false"/>   
         
<!--         
    <plugin
         id="com.springsource.javax.persistence"
         download-size="0"
         install-size="0"
         version="0.0.0"
         unpack="false"/>
 	-->
 	<!-- queryDSL
 	<plugin
         id="com.mysema.querydsl.core"
         download-size="0"
         install-size="0"
         version="0.0.0"
         unpack="false"/>            
    <plugin
         id="com.mysema.commons.lang"
         download-size="0"
         install-size="0"
         version="0.0.0"
         unpack="false"/>            
    <plugin
         id="net.sourceforge.collections.collections-generic.osgi"
         download-size="0"
         install-size="0"
         version="0.0.0"
         unpack="false"/>
    
    <plugin
         id="com.springsource.net.sf.cglib"
         download-size="0"
         install-size="0"
         version="0.0.0"
         unpack="false"/>
        Manque package javax.tools
        TBD : tester avec çà sur une machine windows ou linux... 
         <dependencies>
        <dependency>
          <groupId>com.sun</groupId>
          <artifactId>tools</artifactId>
          <version>1.6.0</version>
          <scope>system</scope>
          <systemPath>${java.home}/../lib/tools.jar</systemPath>
        </dependency>
      </dependencies>      
     -->        
                                     
</feature>
